micro_mastodon_reader-1.1.1.dist-info/licenses/LICENSE
micromastodonreader/__init__.py
micromastodonreader/micro_mastodon_reader.py
micro_mastodon_reader-1.1.1.dist-info/METADATA
micro_mastodon_reader-1.1.1.dist-info/WHEEL
micro_mastodon_reader-1.1.1.dist-info/top_level.txt
micro_mastodon_reader-1.1.1.dist-info/RECORD
