Metadata-Version: 2.4
Name: Micro-Mastodon-Reader
Version: 1.1.1
Summary: Light Mastodon project file reader for Python
Author-email: Christoph Sommer <christoph.sommer23@gmail.com>, Léo Guignard <leo.guignard@univ-amu.fr>
Maintainer-email: Léo Guignard <leo.guignard@univ-amu.fr>
License-Expression: BSD-3-Clause
Project-URL: Bug Tracker, https://github.com/GuignardLab/python-mastodon-importer-light/issues
Project-URL: Documentation, https://github.com/GuignardLab/python-mastodon-importer-light#README.md
Project-URL: Source Code, https://github.com/GuignardLab/python-mastodon-importer-light
Project-URL: User Support, https://github.com/GuignardLab/python-mastodon-importer-light/issues
Classifier: Development Status :: 4 - Beta
Classifier: Intended Audience :: Developers
Classifier: Operating System :: OS Independent
Classifier: Programming Language :: Python
Classifier: Programming Language :: Python :: 3
Classifier: Programming Language :: Python :: 3 :: Only
Classifier: Programming Language :: Python :: 3.10
Classifier: Programming Language :: Python :: 3.11
Classifier: Programming Language :: Python :: 3.12
Classifier: Programming Language :: Python :: 3.13
Requires-Python: >=3.10
License-File: LICENSE
Requires-Dist: numpy
Dynamic: license-file
